weberEnvMail/CEnvZMail.py
weberEnvMail/__init__.py
weberenvmail-0.0.3.dist-info/licenses/LICENSE
weberenvmail-0.0.3.dist-info/METADATA
weberenvmail-0.0.3.dist-info/WHEEL
weberenvmail-0.0.3.dist-info/top_level.txt
weberenvmail-0.0.3.dist-info/RECORD
